kuma_sentinel/__init__.py
kuma_sentinel/py.typed
kuma_sentinel/cli/__init__.py
kuma_sentinel/cli/app.py
kuma_sentinel/cli/commands/__init__.py
kuma_sentinel/cli/commands/base.py
kuma_sentinel/cli/commands/cmdcheck.py
kuma_sentinel/cli/commands/executor.py
kuma_sentinel/cli/commands/kopiasnapshotstatus.py
kuma_sentinel/cli/commands/portscan.py
kuma_sentinel/cli/commands/zfspoolstatus.py
kuma_sentinel/core/__init__.py
kuma_sentinel/core/heartbeat.py
kuma_sentinel/core/logger.py
kuma_sentinel/core/models.py
kuma_sentinel/core/uptime_kuma.py
kuma_sentinel/core/checkers/__init__.py
kuma_sentinel/core/checkers/base.py
kuma_sentinel/core/checkers/cmdcheck_checker.py
kuma_sentinel/core/checkers/kopia_snapshot_checker.py
kuma_sentinel/core/checkers/port_checker.py
kuma_sentinel/core/checkers/zfs_pool_checker.py
kuma_sentinel/core/config/__init__.py
kuma_sentinel/core/config/base.py
kuma_sentinel/core/config/cmdcheck_config.py
kuma_sentinel/core/config/kopia_snapshot_config.py
kuma_sentinel/core/config/portscan_config.py
kuma_sentinel/core/config/zfs_pool_config.py
kuma_sentinel/core/utils/sanitizer.py
kuma_sentinel-0.0.2.dist-info/METADATA
kuma_sentinel-0.0.2.dist-info/WHEEL
kuma_sentinel-0.0.2.dist-info/entry_points.txt
kuma_sentinel-0.0.2.dist-info/licenses/LICENSE
kuma_sentinel-0.0.2.dist-info/RECORD
