Metadata-Version: 2.4
Name: kuma-sentinel
Version: 0.0.2
Summary: Uptime Kuma monitoring agent for internal server monitoring. Execute custom checks, scan ports, monitor backups and storage—then report to Uptime Kuma via push API.
Project-URL: Homepage, https://go.hugobatista.com/gh/kuma-sentinel
Project-URL: Documentation, https://go.hugobatista.com/gh/kuma-sentinel#readme
Project-URL: Repository, https://go.hugobatista.com/gh/kuma-sentinel.git
Project-URL: Issues, https://go.hugobatista.com/gh/kuma-sentinel/issues
Author-email: Hugo Batista <mail@hugobatista.com>
License-Expression: MIT
License-File: LICENSE
Keywords: backup-monitoring,monitoring-agent,network-monitoring,nmap,port-scanner,server-monitoring,system-monitoring,uptime-kuma,uptime-kuma-agent,uptime-monitoring
Classifier: Development Status :: 3 - Alpha
Classifier: Environment :: Console
Classifier: Intended Audience :: Information Technology
Classifier: Intended Audience :: System Administrators
Classifier: License :: OSI Approved :: MIT License
Classifier: Natural Language :: English
Classifier: Operating System :: OS Independent
Classifier: Programming Language :: Python :: 3
Classifier: Programming Language :: Python :: 3.10
Classifier: Programming Language :: Python :: 3.11
Classifier: Programming Language :: Python :: 3.12
Classifier: Topic :: System :: Monitoring
Classifier: Topic :: System :: Networking
Classifier: Topic :: Utilities
Requires-Python: >=3.10
Requires-Dist: click>=8.0.0
Requires-Dist: pyyaml>=6.0
Provides-Extra: dev
Requires-Dist: black>=23.0.0; extra == 'dev'
Requires-Dist: mypy>=1.0.0; extra == 'dev'
Requires-Dist: pytest-cov>=4.0.0; extra == 'dev'
Requires-Dist: pytest>=7.0.0; extra == 'dev'
Requires-Dist: ruff>=0.1.0; extra == 'dev'
